NiukeWangMingqiBishiMianshiQiuzhiGonglveSidaXingye20202021Fix1/README.md
NiukeWangMingqiBishiMianshiQiuzhiGonglveSidaXingye20202021Fix1/__init__.py
NiukeWangMingqiBishiMianshiQiuzhiGonglveSidaXingye20202021Fix1/__main__.py
NiukeWangMingqiBishiMianshiQiuzhiGonglveSidaXingye20202021Fix1/file.epub
NiukeWangMingqiBishiMianshiQiuzhiGonglveSidaXingye20202021Fix1/index.html
NiukeWangMingqiBishiMianshiQiuzhiGonglveSidaXingye20202021Fix1/css/__init__.py
NiukeWangMingqiBishiMianshiQiuzhiGonglveSidaXingye20202021Fix1/css/annotations.css
NiukeWangMingqiBishiMianshiQiuzhiGonglveSidaXingye20202021Fix1/css/main.css
NiukeWangMingqiBishiMianshiQiuzhiGonglveSidaXingye20202021Fix1/css/normalize.css
NiukeWangMingqiBishiMianshiQiuzhiGonglveSidaXingye20202021Fix1/css/popup.css
NiukeWangMingqiBishiMianshiQiuzhiGonglveSidaXingye20202021Fix1/font/__init__.py
NiukeWangMingqiBishiMianshiQiuzhiGonglveSidaXingye20202021Fix1/font/fontello.eot
NiukeWangMingqiBishiMianshiQiuzhiGonglveSidaXingye20202021Fix1/font/fontello.svg
NiukeWangMingqiBishiMianshiQiuzhiGonglveSidaXingye20202021Fix1/font/fontello.ttf
NiukeWangMingqiBishiMianshiQiuzhiGonglveSidaXingye20202021Fix1/font/fontello.woff
NiukeWangMingqiBishiMianshiQiuzhiGonglveSidaXingye20202021Fix1/img/__init__.py
NiukeWangMingqiBishiMianshiQiuzhiGonglveSidaXingye20202021Fix1/img/annotator-glyph-sprite.png
NiukeWangMingqiBishiMianshiQiuzhiGonglveSidaXingye20202021Fix1/img/annotator-icon-sprite.png
NiukeWangMingqiBishiMianshiQiuzhiGonglveSidaXingye20202021Fix1/img/apple-touch-icon.png
NiukeWangMingqiBishiMianshiQiuzhiGonglveSidaXingye20202021Fix1/img/cancelfullscreen.png
NiukeWangMingqiBishiMianshiQiuzhiGonglveSidaXingye20202021Fix1/img/close.png
NiukeWangMingqiBishiMianshiQiuzhiGonglveSidaXingye20202021Fix1/img/fullscreen.png
NiukeWangMingqiBishiMianshiQiuzhiGonglveSidaXingye20202021Fix1/img/loader.gif
NiukeWangMingqiBishiMianshiQiuzhiGonglveSidaXingye20202021Fix1/img/menu-icon.png
niuke_wang_mingqi_bishi_mianshi_qiuzhi_gonglve_sida_xingye_2020_2021_fix1-2025.3.24.1.dist-info/METADATA
niuke_wang_mingqi_bishi_mianshi_qiuzhi_gonglve_sida_xingye_2020_2021_fix1-2025.3.24.1.dist-info/WHEEL
niuke_wang_mingqi_bishi_mianshi_qiuzhi_gonglve_sida_xingye_2020_2021_fix1-2025.3.24.1.dist-info/entry_points.txt
niuke_wang_mingqi_bishi_mianshi_qiuzhi_gonglve_sida_xingye_2020_2021_fix1-2025.3.24.1.dist-info/top_level.txt
niuke_wang_mingqi_bishi_mianshi_qiuzhi_gonglve_sida_xingye_2020_2021_fix1-2025.3.24.1.dist-info/RECORD
